rtd_ae/__init__.py
rtd_ae/autoencoder.py
rtd_ae/custom_shapes.py
rtd_ae/rtd.py
rtd_ae/spheres.py
rtd_ae/top_ae.py
rtd_ae/topology.py
rtd_ae/utils.py
rtd_ae-0.1.2.dist-info/METADATA
rtd_ae-0.1.2.dist-info/WHEEL
rtd_ae-0.1.2.dist-info/RECORD
