Metadata-Version: 2.1
Name: rtd-ae
Version: 0.1.2
Summary: 
Author: Daniil Cherniavskii
Author-email: danchern97@mail.ru
Requires-Python: >=3.9,<3.13
Classifier: Programming Language :: Python :: 3
Classifier: Programming Language :: Python :: 3.9
Classifier: Programming Language :: Python :: 3.10
Classifier: Programming Language :: Python :: 3.11
Requires-Dist: POT (>=0.9.0,<0.10.0)
Requires-Dist: Pillow (>=9.0.0,<10.0.0)
Requires-Dist: giotto-ph (>=0.2,<0.3)
Requires-Dist: gudhi (>=3.6,<4.0)
Requires-Dist: iprogress (>=0.4,<0.5)
Requires-Dist: ipywidgets (>=8,<9)
Requires-Dist: matplotlib (>=3.6,<4.0)
Requires-Dist: notebook (>=6,<7)
Requires-Dist: numpy (>=1.19.0,<2.0.0)
Requires-Dist: pandas (>=2,<3)
Requires-Dist: pytorch-lightning (>=2,<3)
Requires-Dist: scikit-learn (>=1.1,<2.0)
Requires-Dist: scipy (>=1.9,<2.0)
Requires-Dist: tensorboardx (>=2,<3)
Requires-Dist: torch (>=2,<3)
Requires-Dist: tqdm (>=4.60.0,<5.0.0)
